{
  "display": {
    "title": {
      "translate": "advancement.scriptor.community"
    },
    "description": {
      "translate": "advancement.scriptor.community_desc"
    },
    "icon": {
      "id": "scriptor:tome_tier4"
    },
    "frame": "task",
    "show_toast": true,
    "announce_to_chat": true,
    "hidden": true,
    "background": "minecraft:textures/gui/advancements/backgrounds/stone.png"
  },
  "criteria": {
    "collect": {
      "conditions": {
        "player": []
      },
      "trigger": "scriptor:community"
    }
  }
}